Metadata-Version: 1.0
Name: first-distrib
Version: 0.1.1
Summary: Gaussian distributions
Home-page: UNKNOWN
Author: Taufikur Rahman
Author-email: taufiktrf@gmail.com
License: UNKNOWN
Platform: UNKNOWN
